<annotation>  
	  <folder>images</folder>  
	  <filename>004270508.jpg</filename>  
	  <path>C:\Users\Desktop\000508.jpg</path>  
	  <source>    
		    <database>Unknown</database>    
	  </source>  
	  <size>    
		    <width>480</width>    
		    <height>640</height>    
		    <depth>3</depth>    
	  </size>  
	  <segmented>0</segmented>  
	  <object>    
		    <name>bud</name>    
		    <pose>Unspecified</pose>    
		    <truncated>0</truncated>    
		    <difficult>0</difficult>    
		    <bndbox>      
			      <xmin>206</xmin>      
			      <ymin>258</ymin>      
			      <xmax>277</xmax>      
			      <ymax>327</ymax>      
		    </bndbox>    
	  </object>  
</annotation>