<annotation>  
	  <folder>images</folder>  
	  <filename>004270345.jpg</filename>  
	  <path>C:\Users\Desktop\000345.jpg</path>  
	  <source>    
		    <database>Unknown</database>    
	  </source>  
	  <size>    
		    <width>480</width>    
		    <height>640</height>    
		    <depth>3</depth>    
	  </size>  
	  <segmented>0</segmented>  
	  <object>    
		    <name>flower</name>    
		    <pose>Unspecified</pose>    
		    <truncated>1</truncated>    
		    <difficult>0</difficult>    
		    <bndbox>      
			      <xmin>451</xmin>      
			      <ymin>473</ymin>      
			      <xmax>480</xmax>      
			      <ymax>537</ymax>      
		    </bndbox>    
	  </object>  
	  <object>    
		    <name>flower</name>    
		    <pose>Unspecified</pose>    
		    <truncated>0</truncated>    
		    <difficult>0</difficult>    
		    <bndbox>      
			      <xmin>197</xmin>      
			      <ymin>292</ymin>      
			      <xmax>272</xmax>      
			      <ymax>383</ymax>      
		    </bndbox>    
	  </object>  
</annotation>