<annotation>  
	  <folder>images</folder>  
	  <filename>006072615.jpg</filename>  
	  <path>C:\Users\Desktop\002615.jpg</path>  
	  <source>    
		    <database>Unknown</database>    
	  </source>  
	  <size>    
		    <width>480</width>    
		    <height>640</height>    
		    <depth>3</depth>    
	  </size>  
	  <segmented>0</segmented>  
	  <object>    
		    <name>early-fruit</name>    
		    <pose>Unspecified</pose>    
		    <truncated>0</truncated>    
		    <difficult>0</difficult>    
		    <bndbox>      
			      <xmin>124</xmin>      
			      <ymin>272</ymin>      
			      <xmax>302</xmax>      
			      <ymax>425</ymax>      
		    </bndbox>    
	  </object>  
</annotation>