<annotation>  
	  <folder>images</folder>  
	  <filename>008134830.jpg</filename>  
	  <path>C:\Users\Desktop\004830.jpg</path>  
	  <source>    
		    <database>Unknown</database>    
	  </source>  
	  <size>    
		    <width>480</width>    
		    <height>640</height>    
		    <depth>3</depth>    
	  </size>  
	  <segmented>0</segmented>  
	  <object>    
		    <name>ripe</name>    
		    <pose>Unspecified</pose>    
		    <truncated>0</truncated>    
		    <difficult>0</difficult>    
		    <bndbox>      
			      <xmin>116</xmin>      
			      <ymin>314</ymin>      
			      <xmax>235</xmax>      
			      <ymax>486</ymax>      
		    </bndbox>    
	  </object>  
	  <object>    
		    <name>ripe</name>    
		    <pose>Unspecified</pose>    
		    <truncated>0</truncated>    
		    <difficult>0</difficult>    
		    <bndbox>      
			      <xmin>190</xmin>      
			      <ymin>159</ymin>      
			      <xmax>356</xmax>      
			      <ymax>286</ymax>      
		    </bndbox>    
	  </object>  
</annotation>