<annotation>  
	  <folder>images</folder>  
	  <filename>006032480.jpg</filename>  
	  <path>C:\Users\Desktop\002480.jpg</path>  
	  <source>    
		    <database>Unknown</database>    
	  </source>  
	  <size>    
		    <width>480</width>    
		    <height>640</height>    
		    <depth>3</depth>    
	  </size>  
	  <segmented>0</segmented>  
	  <object>    
		    <name>flower</name>    
		    <pose>Unspecified</pose>    
		    <truncated>0</truncated>    
		    <difficult>0</difficult>    
		    <bndbox>      
			      <xmin>79</xmin>      
			      <ymin>552</ymin>      
			      <xmax>102</xmax>      
			      <ymax>580</ymax>      
		    </bndbox>    
	  </object>  
	  <object>    
		    <name>flower</name>    
		    <pose>Unspecified</pose>    
		    <truncated>0</truncated>    
		    <difficult>0</difficult>    
		    <bndbox>      
			      <xmin>118</xmin>      
			      <ymin>332</ymin>      
			      <xmax>148</xmax>      
			      <ymax>365</ymax>      
		    </bndbox>    
	  </object>  
	  <object>    
		    <name>flower</name>    
		    <pose>Unspecified</pose>    
		    <truncated>0</truncated>    
		    <difficult>0</difficult>    
		    <bndbox>      
			      <xmin>263</xmin>      
			      <ymin>603</ymin>      
			      <xmax>286</xmax>      
			      <ymax>627</ymax>      
		    </bndbox>    
	  </object>  
	  <object>    
		    <name>flower</name>    
		    <pose>Unspecified</pose>    
		    <truncated>0</truncated>    
		    <difficult>0</difficult>    
		    <bndbox>      
			      <xmin>296</xmin>      
			      <ymin>440</ymin>      
			      <xmax>357</xmax>      
			      <ymax>513</ymax>      
		    </bndbox>    
	  </object>  
	  <object>    
		    <name>early-fruit</name>    
		    <pose>Unspecified</pose>    
		    <truncated>0</truncated>    
		    <difficult>0</difficult>    
		    <bndbox>      
			      <xmin>179</xmin>      
			      <ymin>55</ymin>      
			      <xmax>243</xmax>      
			      <ymax>103</ymax>      
		    </bndbox>    
	  </object>  
	  <object>    
		    <name>early-fruit</name>    
		    <pose>Unspecified</pose>    
		    <truncated>0</truncated>    
		    <difficult>0</difficult>    
		    <bndbox>      
			      <xmin>150</xmin>      
			      <ymin>494</ymin>      
			      <xmax>214</xmax>      
			      <ymax>542</ymax>      
		    </bndbox>    
	  </object>  
	  <object>    
		    <name>flower</name>    
		    <pose>Unspecified</pose>    
		    <truncated>0</truncated>    
		    <difficult>0</difficult>    
		    <bndbox>      
			      <xmin>329</xmin>      
			      <ymin>424</ymin>      
			      <xmax>413</xmax>      
			      <ymax>512</ymax>      
		    </bndbox>    
	  </object>  
	  <object>    
		    <name>flower</name>    
		    <pose>Unspecified</pose>    
		    <truncated>0</truncated>    
		    <difficult>0</difficult>    
		    <bndbox>      
			      <xmin>82</xmin>      
			      <ymin>370</ymin>      
			      <xmax>120</xmax>      
			      <ymax>414</ymax>      
		    </bndbox>    
	  </object>  
	  <object>    
		    <name>flower</name>    
		    <pose>Unspecified</pose>    
		    <truncated>0</truncated>    
		    <difficult>0</difficult>    
		    <bndbox>      
			      <xmin>165</xmin>      
			      <ymin>282</ymin>      
			      <xmax>308</xmax>      
			      <ymax>420</ymax>      
		    </bndbox>    
	  </object>  
</annotation>