<annotation>  
	  <folder>images</folder>  
	  <filename>008315430.jpg</filename>  
	  <path>C:\Users\Desktop\005430.jpg</path>  
	  <source>    
		    <database>Unknown</database>    
	  </source>  
	  <size>    
		    <width>480</width>    
		    <height>640</height>    
		    <depth>3</depth>    
	  </size>  
	  <segmented>0</segmented>  
	  <object>    
		    <name>ripe</name>    
		    <pose>Unspecified</pose>    
		    <truncated>0</truncated>    
		    <difficult>0</difficult>    
		    <bndbox>      
			      <xmin>151</xmin>      
			      <ymin>582</ymin>      
			      <xmax>181</xmax>      
			      <ymax>634</ymax>      
		    </bndbox>    
	  </object>  
	  <object>    
		    <name>ripe</name>    
		    <pose>Unspecified</pose>    
		    <truncated>0</truncated>    
		    <difficult>0</difficult>    
		    <bndbox>      
			      <xmin>135</xmin>      
			      <ymin>283</ymin>      
			      <xmax>173</xmax>      
			      <ymax>330</ymax>      
		    </bndbox>    
	  </object>  
	  <object>    
		    <name>ripe</name>    
		    <pose>Unspecified</pose>    
		    <truncated>0</truncated>    
		    <difficult>0</difficult>    
		    <bndbox>      
			      <xmin>392</xmin>      
			      <ymin>235</ymin>      
			      <xmax>437</xmax>      
			      <ymax>278</ymax>      
		    </bndbox>    
	  </object>  
	  <object>    
		    <name>ripe</name>    
		    <pose>Unspecified</pose>    
		    <truncated>0</truncated>    
		    <difficult>0</difficult>    
		    <bndbox>      
			      <xmin>171</xmin>      
			      <ymin>226</ymin>      
			      <xmax>268</xmax>      
			      <ymax>334</ymax>      
		    </bndbox>    
	  </object>  
	  <object>    
		    <name>ripe</name>    
		    <pose>Unspecified</pose>    
		    <truncated>0</truncated>    
		    <difficult>0</difficult>    
		    <bndbox>      
			      <xmin>263</xmin>      
			      <ymin>291</ymin>      
			      <xmax>371</xmax>      
			      <ymax>390</ymax>      
		    </bndbox>    
	  </object>  
</annotation>